gdbot/__init__.py
gdbot/config.py
gdbot/gdbot.py
gdbot-1.1.0.dist-info/LICENSE
gdbot-1.1.0.dist-info/METADATA
gdbot-1.1.0.dist-info/WHEEL
gdbot-1.1.0.dist-info/top_level.txt
gdbot-1.1.0.dist-info/RECORD
