Metadata-Version: 2.1
Name: gdbot
Version: 1.1.0
Summary: Python Library for creating Geometry Dash Comment Bots.
Home-page: https://github.com/SevenworksDev/GDBotPy
Author: SevenworksDev
Author-email: mail@sevenworks.eu.org
License: MIT
Platform: UNKNOWN
Classifier: Programming Language :: Python :: 3
Classifier: License :: OSI Approved :: MIT License
Classifier: Operating System :: OS Independent
Requires-Python: >=3.7
License-File: LICENSE
Requires-Dist: requests
